{"ocr_type": "receipts", "request_id": "P_212.106.162.69_lmma8fg4_2lh", "ref_no": "oct_python_123", "file_name": "20230114_172310.jpg", "request_received_on": 1694884102708, "success": true, "image_width": 1264, "image_height": 1064, "image_rotation": 0, "recognition_completed_on": 1694884103588, "receipts": [{"merchant_name": "Anna P\u0142aszczyk 44-117 Gliwice", "merchant_address": "ul. Jowisza 1a", "merchant_phone": null, "merchant_website": null, "merchant_tax_reg_no": null, "merchant_company_reg_no": null, "region": null, "mall": null, "country": "US", "receipt_no": "kasjer_3", "date": "2022-12-05", "time": "17:51", "items": [{"amount": 6.2, "category": null, "description": "NAPOJ LIPTON 11-A1szt", "flags": "A", "qty": null, "remarks": null, "tags": null, "unitPrice": 6.2}, {"amount": 6.2, "category": null, "description": "SPRZEDAZ OPODATKOWANA A", "flags": "", "qty": null, "remarks": null, "tags": null, "unitPrice": null}, {"amount": 1.16, "category": null, "description": "PTU A 23%", "flags": "", "qty": null, "remarks": null, "tags": null, "unitPrice": null}, {"amount": 1.16, "category": null, "description": "SUMA PTU", "flags": "", "qty": null, "remarks": null, "tags": null, "unitPrice": null}, {"amount": 6.2, "category": null, "description": "SUMA PLN", "flags": "", "qty": null, "remarks": null, "tags": null, "unitPrice": null}, {"amount": 6.2, "category": null, "description": "INNA Karta kred", "flags": " PLN", "qty": null, "remarks": null, "tags": null, "unitPrice": null}], "currency": "USD", "total": 6.2, "subtotal": null, "tax": null, "service_charge": null, "tip": null, "payment_method": null, "payment_details": null, "credit_card_type": null, "credit_card_number": null, "ocr_text": "                   Sklep Zabka 25252\n                     Anna P\u0142aszczyk\n                     44-117 Gliwice\n                     ul. Jowisza 1a\n                                                   : 17984\n NIP 6312700874\n            PARAGON FISKALNY\n NAPOJ LIPTON 11-A                     1szt. x6,20 6,20A\n SPRZEDAZ OPODATKOWANA A                             6,20\n PTU A 23%                                           1,16\n SUMA PTU                                            1.16\n SUMA PLN                                       6,20\n ROZLICZENIE P\u0141ATNO\u015aCI\n INNA Karta kred.                               6,20 PLN\n 00076 #z5252-2 kasjer_3                2022-12-05 17:51\n        B00FD74C40EDDDC763B5D2EE 1FA89EDAFBAEF832\n                       EAO 2001620411\n                     Nr sys 15982", "ocr_confidence": 93.8, "width": 1150, "height": 951, "avg_char_width": 19.8214, "avg_line_height": 40.5806, "conf_amount": 89, "source_locations": {"date": [[{"y": 854, "x": 804}, {"y": 854, "x": 1165}, {"y": 905, "x": 1165}, {"y": 905, "x": 804}]], "receipt_no": [[{"y": 852, "x": 24}, {"y": 854, "x": 510}, {"y": 902, "x": 510}, {"y": 899, "x": 24}]], "merchant_name": [[{"y": 221, "x": 432}, {"y": 217, "x": 746}, {"y": 263, "x": 747}, {"y": 267, "x": 433}]], "doc": [[{"y": 57, "x": -24}, {"y": 57, "x": 1240}, {"y": 1103, "x": 1240}, {"y": 1103, "x": -24}]], "merchant_address": [[{"y": 275, "x": 433}, {"y": 270, "x": 744}, {"y": 312, "x": 745}, {"y": 318, "x": 434}]]}}]}